HUST_PPS/__init__.py
HUST_PPS/horner.py
HUST_PPS/mocNoiSuy.py
HUST_PPS/noiSuyLagrange.py
HUST_PPS/noiSuyNewton.py
HUST_PPS/noiSuyTrungTam.py
HUST_PPS/utils.py
HUST_PPS-0.3.0.dist-info/LICENSE
HUST_PPS-0.3.0.dist-info/METADATA
HUST_PPS-0.3.0.dist-info/WHEEL
HUST_PPS-0.3.0.dist-info/top_level.txt
HUST_PPS-0.3.0.dist-info/RECORD
