Metadata-Version: 2.1
Name: HUST_PPS
Version: 0.3.0
License-File: LICENSE
Requires-Dist: numpy>=2.1.1
